fpppy/__init__.py
fpppy/models.py
fpppy/utils.py
fpppy-0.0.3.dist-info/licenses/LICENSE
fpppy-0.0.3.dist-info/METADATA
fpppy-0.0.3.dist-info/WHEEL
fpppy-0.0.3.dist-info/top_level.txt
fpppy-0.0.3.dist-info/RECORD
