Metadata-Version: 2.4
Name: fpppy
Version: 0.0.3
Requires-Python: >=3.8
License-File: LICENSE
Requires-Dist: matplotlib
Requires-Dist: pre-commit
Requires-Dist: pytest
Requires-Dist: pytest-cov
Requires-Dist: scikit-learn
Requires-Dist: statsmodels
Requires-Dist: utilsforecast
Dynamic: license-file
